secfsdstools/__init__.py
secfsdstools/a_config/__init__.py
secfsdstools/a_config/configmgt.py
secfsdstools/a_config/configmodel.py
secfsdstools/a_utils/__init__.py
secfsdstools/a_utils/basic.py
secfsdstools/a_utils/constants.py
secfsdstools/a_utils/dbutils.py
secfsdstools/a_utils/downloadutils.py
secfsdstools/a_utils/fileutils.py
secfsdstools/a_utils/parallelexecution.py
secfsdstools/a_utils/version.py
secfsdstools/b_setup/__init__.py
secfsdstools/b_setup/setupdb.py
secfsdstools/b_setup/sql/V2__create_parquet_report_index.sql
secfsdstools/b_setup/sql/V3__create_status.sql
secfsdstools/b_setup/sql/V4__delete_zip_tables.sql
secfsdstools/c_automation/__init__.py
secfsdstools/c_automation/automation_utils.py
secfsdstools/c_automation/task_framework.py
secfsdstools/c_daily/__init__.py
secfsdstools/c_daily/dailypreparation_process.py
secfsdstools/c_download/__init__.py
secfsdstools/c_download/basedownloading_process.py
secfsdstools/c_download/secdownloading_process.py
secfsdstools/c_index/__init__.py
secfsdstools/c_index/companyindexreading.py
secfsdstools/c_index/indexdataaccess.py
secfsdstools/c_index/indexing_process.py
secfsdstools/c_index/searching.py
secfsdstools/c_transform/__init__.py
secfsdstools/c_transform/toparquettransforming_process.py
secfsdstools/c_update/__init__.py
secfsdstools/c_update/updateprocess.py
secfsdstools/c_update_check/__init__.py
secfsdstools/d_container/__init__.py
secfsdstools/d_container/databagmodel.py
secfsdstools/d_container/filter.py
secfsdstools/d_container/presentation.py
secfsdstools/e_collector/__init__.py
secfsdstools/e_collector/basecollector.py
secfsdstools/e_collector/companycollecting.py
secfsdstools/e_collector/multireportcollecting.py
secfsdstools/e_collector/reportcollecting.py
secfsdstools/e_collector/zipcollecting.py
secfsdstools/e_filter/__init__.py
secfsdstools/e_filter/joinedfiltering.py
secfsdstools/e_filter/rawfiltering.py
secfsdstools/e_presenter/__init__.py
secfsdstools/e_presenter/presenting.py
secfsdstools-2.4.3.dist-info/LICENSE
secfsdstools-2.4.3.dist-info/METADATA
secfsdstools-2.4.3.dist-info/WHEEL
secfsdstools-2.4.3.dist-info/RECORD
