Metadata-Version: 2.3
Name: secfsdstools
Version: 2.4.3
Summary: A few python tools to analyze the SEC.gov financial statements data sets (https://www.sec.gov/dera/data/financial-statement-data-sets)
License: Apache-2.0
Keywords: SEC.GOV,SEC EDGAR,SEC Filing,EDGAR,Finance,CIK,10-Q,10-K,8-K,Financial Statements,Financial Statements Dataset,Financial Analysis,Data Processing,Financial Data,SEC API,XBRL
Author: Hansjoerg
Author-email: hansjoerg.wingeier@gmail.com
Maintainer: Hansjoerg Wingeier
Maintainer-email: hansjoeg.wingeier@gmail.com
Requires-Python: >=3.10
Classifier: Development Status :: 5 - Production/Stable
Classifier: Programming Language :: Python :: 3
Classifier: Programming Language :: Python :: 3.10
Classifier: Programming Language :: Python :: 3.11
Classifier: Programming Language :: Python :: 3.12
Classifier: License :: OSI Approved :: Apache Software License
Classifier: Operating System :: OS Independent
Classifier: Topic :: Office/Business :: Financial
Classifier: Topic :: Office/Business :: Financial :: Investment
Classifier: Intended Audience :: Developers
Classifier: Intended Audience :: Financial and Insurance Industry
Classifier: Topic :: Software Development :: Libraries :: Python Modules
Classifier: Topic :: Utilities
Classifier: Natural Language :: English
Provides-Extra: dev
Requires-Dist: coverage (>=7.0,<8.0) ; extra == "dev"
Requires-Dist: fastparquet (>=0.5)
Requires-Dist: numpy (>=1.0,<2.0)
Requires-Dist: pandas (>=1.3)
Requires-Dist: pandera (==0.22.1)
Requires-Dist: pathos (>=0.3,<1.0)
Requires-Dist: pdoc3 (>=0.10,<1.0) ; extra == "dev"
Requires-Dist: pyarrow (>=8.0)
Requires-Dist: pylint (>=3.0,<4.0) ; extra == "dev"
Requires-Dist: pytest (>=8.3,<9.0) ; extra == "dev"
Requires-Dist: requests (>=2.0)
Requires-Dist: ruff ; extra == "dev"
Requires-Dist: secdaily (>=0.2.2)
Requires-Dist: typing_extensions (>=4.0,<5.0) ; extra == "dev"
Project-URL: Bug Tracker, https://github.com/HansjoergW/sec-fincancial-statement-data-set/issues
Project-URL: Change Log, https://github.com/HansjoergW/sec-fincancial-statement-data-set/blob/main/CHANGELOG.md
Project-URL: Funding, https://github.com/sponsors/HansjoergW
Project-URL: Forum, https://github.com/HansjoergW/sec-fincancial-statement-data-set/discussions
Project-URL: Github, https://github.com/HansjoergW/sec-fincancial-statement-data-set
Project-URL: Homepage, https://hansjoergw.github.io/sec-fincancial-statement-data-set/
